{
"type": "FeatureCollection",
"crs": { "type": "name", "properties": { "name": "urn:ogc:def:crs:OGC:1.3:CRS84" } },
                                                                                
"features": [
{ "type": "Feature", "properties": { "id": 4, "name": "Ambrym", "XCOORD": 168.113678, "YCOORD": -16.261450 }, "geometry": { "type": "Point", "coordinates": [ 168.11367813296141, -16.261449727100104 ] } },
{ "type": "Feature", "properties": { "id": 3, "name": "Santo", "XCOORD": 167.674799, "YCOORD": -16.428152 }, "geometry": { "type": "Point", "coordinates": [ 167.67479870781892, -16.428151838349152 ] } },
{ "type": "Feature", "properties": { "id": 2, "name": "Efate", "XCOORD": 168.378834, "YCOORD": -17.669419 }, "geometry": { "type": "Point", "coordinates": [ 168.37883445231836, -17.669419170833649 ] } },
{ "type": "Feature", "properties": { "id": 1, "name": "Tanna", "XCOORD": 169.293167, "YCOORD": -19.497973 }, "geometry": { "type": "Point", "coordinates": [ 169.29316658803185, -19.497972538936573 ] } }
]
}
